py_parser_sber/__init__.py
py_parser_sber/abstract.py
py_parser_sber/logging.json
py_parser_sber/main.py
py_parser_sber/sberbank_parse.py
py_parser_sber/utils.py
py_parser_sber-0.7.0.dist-info/LICENSE.md
py_parser_sber-0.7.0.dist-info/METADATA
py_parser_sber-0.7.0.dist-info/WHEEL
py_parser_sber-0.7.0.dist-info/entry_points.txt
py_parser_sber-0.7.0.dist-info/top_level.txt
py_parser_sber-0.7.0.dist-info/RECORD
