Metadata-Version: 2.1
Name: py-parser-sber
Version: 0.7.0
Summary: Simple parser of Sberbank, using selenium
Home-page: https://github.com/Niccolum/py_parse_sber
Author: Nikolai Vidov
Author-email: lastsal@mail.ru
License: MIT
Keywords: parser sber Sberbank
Platform: any
Classifier: Development Status :: 4 - Beta
Classifier: Environment :: Web Environment
Classifier: Intended Audience :: End Users/Desktop
Classifier: License :: OSI Approved :: MIT License
Classifier: Operating System :: OS Independent
Classifier: Programming Language :: Python
Classifier: Programming Language :: Python :: 3.6
Classifier: Programming Language :: Python :: 3.7
Classifier: Programming Language :: Python :: Implementation :: CPython
Classifier: Programming Language :: Python :: Implementation :: PyPy
Classifier: Topic :: Internet :: WWW/HTTP
Classifier: Topic :: Software Development :: Libraries :: Python Modules
Requires-Python: >=3.6
Requires-Dist: requests (==2.22.0)
Requires-Dist: selenium (==3.141.0)
Provides-Extra: all
Requires-Dist: cohesion ; extra == 'all'
Requires-Dist: flake8 ; extra == 'all'
Requires-Dist: flake8-broken-line ; extra == 'all'
Requires-Dist: flake8-bugbear ; extra == 'all'
Requires-Dist: flake8-builtins ; extra == 'all'
Requires-Dist: flake8-cognitive-complexity ; extra == 'all'
Requires-Dist: flake8-comprehensions ; extra == 'all'
Requires-Dist: flake8-docstrings ; extra == 'all'
Requires-Dist: flake8-fixme ; extra == 'all'
Requires-Dist: flake8-import-order ; extra == 'all'
Requires-Dist: flake8-mutable ; extra == 'all'
Requires-Dist: flake8-mypy ; extra == 'all'
Requires-Dist: flake8-print ; extra == 'all'
Requires-Dist: pep8-naming ; extra == 'all'
Requires-Dist: radon ; extra == 'all'
Requires-Dist: bandit ; extra == 'all'
Requires-Dist: Sphinx ; extra == 'all'
Requires-Dist: pytest ; extra == 'all'
Provides-Extra: docs
Requires-Dist: Sphinx ; extra == 'docs'
Provides-Extra: static_analysis
Requires-Dist: cohesion ; extra == 'static_analysis'
Requires-Dist: flake8 ; extra == 'static_analysis'
Requires-Dist: flake8-broken-line ; extra == 'static_analysis'
Requires-Dist: flake8-bugbear ; extra == 'static_analysis'
Requires-Dist: flake8-builtins ; extra == 'static_analysis'
Requires-Dist: flake8-cognitive-complexity ; extra == 'static_analysis'
Requires-Dist: flake8-comprehensions ; extra == 'static_analysis'
Requires-Dist: flake8-docstrings ; extra == 'static_analysis'
Requires-Dist: flake8-fixme ; extra == 'static_analysis'
Requires-Dist: flake8-import-order ; extra == 'static_analysis'
Requires-Dist: flake8-mutable ; extra == 'static_analysis'
Requires-Dist: flake8-mypy ; extra == 'static_analysis'
Requires-Dist: flake8-print ; extra == 'static_analysis'
Requires-Dist: pep8-naming ; extra == 'static_analysis'
Requires-Dist: radon ; extra == 'static_analysis'
Provides-Extra: tests
Requires-Dist: pytest ; extra == 'tests'
Provides-Extra: vulnerability_check
Requires-Dist: bandit ; extra == 'vulnerability_check'
